bukka/__init__.py
bukka/bukka.py
bukka/coding/__init__.py
bukka/expert_system/__init__.py
bukka/logistics/__init__.py
bukka/logistics/project.py
bukka/logistics/environment/environment.py
bukka/logistics/files/__init__.py
bukka/logistics/files/file_manager.py
bukka/utils/__init__.py
bukka/utils/bukka_logger.py
bukka/utils/reference.py
bukka-0.0.2.dist-info/licenses/LICENSE
bukka-0.0.2.dist-info/METADATA
bukka-0.0.2.dist-info/WHEEL
bukka-0.0.2.dist-info/top_level.txt
bukka-0.0.2.dist-info/RECORD
